click_extra/__init__.py
click_extra/__main__.py
click_extra/_types.py
click_extra/cli.py
click_extra/colorize.py
click_extra/commands.py
click_extra/config.py
click_extra/decorators.py
click_extra/docs_update.py
click_extra/envvar.py
click_extra/logging.py
click_extra/parameters.py
click_extra/py.typed
click_extra/pygments.py
click_extra/pytest.py
click_extra/sphinx/__init__.py
click_extra/sphinx/alerts.py
click_extra/sphinx/click.py
click_extra/table.py
click_extra/telemetry.py
click_extra/testing.py
click_extra/timer.py
click_extra/types.py
click_extra/version.py
click_extra-7.4.0.dist-info/WHEEL
click_extra-7.4.0.dist-info/entry_points.txt
click_extra-7.4.0.dist-info/METADATA
click_extra-7.4.0.dist-info/RECORD
