Metadata-Version: 2.3
Name: click-extra
Version: 7.4.0
Summary: 🌈 Drop-in replacement for Click to make user-friendly and colorful CLI
Keywords: ansi-colors,cli,cloup,colorization,configuration,console,ini,json,json5,jsonc,hjson,logging,multiplatform,pygments,pytest,python,python-tabulate,sphinx,terminal,toml,xml,yaml
Author: Kevin Deldycke
Author-email: Kevin Deldycke <kevin@deldycke.com>
Classifier: Development Status :: 5 - Production/Stable
Classifier: Environment :: Console
Classifier: Environment :: Plugins
Classifier: Framework :: Pytest
Classifier: Framework :: Sphinx
Classifier: Framework :: Sphinx :: Extension
Classifier: Framework :: Sphinx :: Theme
Classifier: Intended Audience :: Developers
Classifier: License :: OSI Approved :: GNU General Public License v2 or later (GPLv2+)
Classifier: Operating System :: MacOS :: MacOS X
Classifier: Operating System :: Microsoft :: Windows
Classifier: Operating System :: POSIX :: BSD :: FreeBSD
Classifier: Operating System :: POSIX :: BSD :: NetBSD
Classifier: Operating System :: POSIX :: BSD :: OpenBSD
Classifier: Operating System :: POSIX :: Linux
Classifier: Programming Language :: Python :: 3
Classifier: Programming Language :: Python :: 3.10
Classifier: Programming Language :: Python :: 3.11
Classifier: Programming Language :: Python :: 3.12
Classifier: Programming Language :: Python :: 3.13
Classifier: Programming Language :: Python :: 3.14
Classifier: Programming Language :: Python :: Implementation :: CPython
Classifier: Topic :: Documentation :: Sphinx
Classifier: Topic :: Software Development :: Libraries :: Python Modules
Classifier: Topic :: Software Development :: User Interfaces
Classifier: Topic :: System :: Logging
Classifier: Topic :: System :: Shells
Classifier: Topic :: Terminals
Classifier: Topic :: Text Processing :: Filters
Classifier: Topic :: Text Processing :: Markup :: HTML
Classifier: Topic :: Text Processing :: Markup :: Markdown
Classifier: Topic :: Text Processing :: Markup :: XML
Classifier: Topic :: Text Processing :: Markup :: reStructuredText
Classifier: Topic :: Utilities
Classifier: Typing :: Typed
Requires-Dist: boltons>=25.0.0
Requires-Dist: click>=8.3.1
Requires-Dist: cloup>=3.0.7
Requires-Dist: deepmerge>=2.0
Requires-Dist: extra-platforms>=5.0.0
Requires-Dist: requests>=2.32.5
Requires-Dist: tabulate[widechars]>=0.9
Requires-Dist: tomli>=2.3.0 ; python_full_version < '3.11'
Requires-Dist: wcmatch>=10.0
Requires-Dist: hjson>=3.1.0 ; extra == 'hjson'
Requires-Dist: json5>=0.12.1 ; extra == 'json5'
Requires-Dist: json-with-comments>=1.2.10 ; extra == 'jsonc'
Requires-Dist: pygments>=2.14 ; extra == 'pygments'
Requires-Dist: pygments-ansi-color>=0.3.0 ; extra == 'pygments'
Requires-Dist: pytest>=9.0.0 ; extra == 'pytest'
Requires-Dist: docutils>=0.20 ; extra == 'sphinx'
Requires-Dist: pygments>=2.14 ; extra == 'sphinx'
Requires-Dist: pygments-ansi-color>=0.3.0 ; extra == 'sphinx'
Requires-Dist: sphinx>=8.0.0 ; extra == 'sphinx'
Requires-Dist: xmltodict>=1.0.0 ; extra == 'xml'
Requires-Dist: pyyaml>=6.0.3 ; extra == 'yaml'
Requires-Python: >=3.10
Project-URL: Changelog, https://github.com/kdeldycke/click-extra/blob/main/changelog.md
Project-URL: Documentation, https://kdeldycke.github.io/click-extra
Project-URL: Funding, https://github.com/sponsors/kdeldycke
Project-URL: Homepage, https://github.com/kdeldycke/click-extra
Project-URL: Issues, https://github.com/kdeldycke/click-extra/issues
Project-URL: Repository, https://github.com/kdeldycke/click-extra
Provides-Extra: hjson
Provides-Extra: json5
Provides-Extra: jsonc
Provides-Extra: pygments
Provides-Extra: pytest
Provides-Extra: sphinx
Provides-Extra: xml
Provides-Extra: yaml
